gcpsecurity/__init__.py
gcpsecurity/gcp_app_engine.py
gcpsecurity/gcp_cloud_sql.py
gcpsecurity/gcp_data_proc.py
gcpsecurity/gcp_gcs.py
gcpsecurity/gcp_gke.py
gcpsecurity/gcp_iam.py
gcpsecurity/gcp_vm.py
gcpsecurity/gcp_vpc.py
gcpsecurity-0.0.6.dist-info/LICENSE
gcpsecurity-0.0.6.dist-info/METADATA
gcpsecurity-0.0.6.dist-info/WHEEL
gcpsecurity-0.0.6.dist-info/top_level.txt
gcpsecurity-0.0.6.dist-info/RECORD
