Metadata-Version: 2.1
Name: gcpsecurity
Version: 0.0.6
Summary: Small package used to analyze or improve gcp security of GCP cloud resources
Home-page: https://github.com/Aadeshkale/gcp-security
Author: Aadesh Kale
Author-email: aadeshkale619@gmail.com
License: UNKNOWN
Platform: UNKNOWN
Classifier: Programming Language :: Python :: 3
Classifier: License :: OSI Approved :: MIT License
Classifier: Operating System :: OS Independent
Requires-Python: >=3.6
Requires-Dist: google-api-python-client (>=1.11.0)
